frereg/__init__.py
frereg/_dct.py
frereg/_freqreg_eva.py
frereg-0.1.0.dist-info/LICENSE
frereg-0.1.0.dist-info/METADATA
frereg-0.1.0.dist-info/WHEEL
frereg-0.1.0.dist-info/top_level.txt
frereg-0.1.0.dist-info/RECORD
