Metadata-Version: 2.1
Name: frereg
Version: 0.1.0
Summary: Frequency Regularization Python Package
Home-page: https://github.com/guanfangdong/pytorch-frequency-regularization
Author: Zhao, Chenqiu and Dong, Guanfang and Zhang, Shupei and Tan, Zijie and Basu, Anup
License: Apache License 2.0
Classifier: Development Status :: 5 - Production/Stable
Classifier: License :: OSI Approved :: Apache Software License
Classifier: Programming Language :: Python :: 3 :: Only
Requires-Python: >=3.8, <3.12
License-File: LICENSE
Requires-Dist: numpy
Requires-Dist: imageio
Requires-Dist: torch
Requires-Dist: matplotlib
